README.txt
setup.py
Products/__init__.py
Products.FSDump.egg-info/PKG-INFO
Products.FSDump.egg-info/SOURCES.txt
Products.FSDump.egg-info/dependency_links.txt
Products.FSDump.egg-info/namespace_packages.txt
Products.FSDump.egg-info/not-zip-safe
Products.FSDump.egg-info/requires.txt
Products.FSDump.egg-info/top_level.txt
Products/FSDump/Dumper.py
Products/FSDump/README.txt
Products/FSDump/__init__.py
Products/FSDump/version.txt
Products/FSDump/interfaces/MetatypeDumper.py
Products/FSDump/interfaces/__init__.py
Products/FSDump/www/addDumper.zpt
Products/FSDump/www/dumper.gif
Products/FSDump/www/editDumper.zpt
docs/CHANGES.rst
docs/COPYRIGHT.txt
docs/Dumper_editForm.rst
docs/INSTALL.rst
docs/LICENSE.txt
docs/Makefile
docs/Mappings.rst
docs/Overview.rst
docs/TODO.rst
docs/conf.py
docs/index.rst