Metadata-Version: 1.0
Name: Products.FSDump
Version: FSDump-0.9.4
Summary: Dump through-the-web Zope objects to the filesystem
Home-page: http://pypi.python.org/pypi/Products.FSDump
Author: Tres Seaver
Author-email: tseaver@agendaless.com
License: ZPL 2.1 (http://www.zope.org/Resources/License/ZPL-2.1)
Keywords: web application server zope zope2
Platform: UNKNOWN
Classifier: Development Status :: 5 - Production/Stable
Classifier: Framework :: Plone
Classifier: Framework :: Zope2
Classifier: Intended Audience :: Developers
Classifier: License :: OSI Approved :: Zope Public License
Classifier: Programming Language :: Python
Classifier: Topic :: Software Development
Classifier: Topic :: Software Development :: Libraries :: Application Frameworks
